a5/__init__.py
a5/version
a5/version.py
a5/ai/__init__.py
a5/ai/llm.py
a5/security/__init__.py
a5/security/crypto.py
a5/utils/__init__.py
a5/utils/jsonl.py
a5/web/__init__.py
a5/web/basic_web_server.py
a5/web/cookies.py
a5/web/http_status_codes.py
a5/web/static_file_server.py
a5/web/tiny_web_server.py
a5/web/tls.py
a5/web/wsgi_server.py
a5-0.0.16.dist-info/METADATA
a5-0.0.16.dist-info/WHEEL
a5-0.0.16.dist-info/top_level.txt
a5-0.0.16.dist-info/RECORD
