Metadata-Version: 2.4
Name: a5
Version: 0.0.16
Author: Aapeli
Requires-Python: >=3.9
Requires-Dist: openai>=2.7.1
Requires-Dist: pydantic>=2.12.4
Requires-Dist: ruff>=0.12.5
Dynamic: author
Dynamic: requires-python
